[
  { "id": "2fef1a77-a1f8-42a3-9293-437a6f4fc5cc", "name": "Wolfstream", "logo_url": "https://wolfstream.tv/xfst_images/wolfstream.tv3.png" },
  { "id": "d460ba6c-5b2e-4cc9-a09e-eda5d5a7e12c", "name": "Fastream", "logo_url": "https://fastream.to/images/logo.png" },
  { "id": "0a635277-c262-4777-8833-caa37e6ec1a8", "name": "Streamhub", "logo_url": "https://streamhub.to/images2/STREAMHUB_LOGO.png" },
  { "id": "ab535237-2262-4763-2443-dfec1a6ec1b9", "name": "Vidhide", "logo_url": "https://vidhide.com/vidhide/images/logo.svg" },
  { "id": "baa39748-8402-4378-b296-3ca653e97f9a", "name": "Doodstream", "logo_url": "https://i.doodcdn.co/img/logo-s.png" },
  { "id": "35677ea5-3641-4319-ae6f-1fe145c9b797", "name": "Lulustream", "logo_url": "https://a.lulucdn.com/static/images/logo.svg" },
  { "id": "9d2f867d-540d-449b-8064-fa4be9100019", "name": "Streamtape", "logo_url": "https://streamtape.com/images/Logo@2x.png" }
]